facex/__init__.py
facex/core.py
facex/utils.py
facex/assets/haarcascade_frontalface_default.xml
facex/assets/model_optimized.tflite
facex-1.1.0.dist-info/LICENSE
facex-1.1.0.dist-info/METADATA
facex-1.1.0.dist-info/WHEEL
facex-1.1.0.dist-info/top_level.txt
facex-1.1.0.dist-info/RECORD
