Metadata-Version: 2.1
Name: facex
Version: 1.1.0
Summary: Lightweight, High-Performance Facial Expression Classifier
Home-page: https://github.com/hfahrudin/facex
Author: Hasby Fahrudin
Author-email: fahrudinhasby12@gmail.com
Classifier: Programming Language :: Python :: 3
Classifier: License :: OSI Approved :: MIT License
Classifier: Operating System :: OS Independent
Requires-Python: >=3.6
License-File: LICENSE
Requires-Dist: scikit-image>=0.16.2
Requires-Dist: tensorflow>=2.0.0
Requires-Dist: opencv-contrib-python>=4.10.0.84
